impyute/__init__.py
impyute/dataset/__init__.py
impyute/dataset/base.py
impyute/dataset/corrupt.py
impyute/deletion/__init__.py
impyute/deletion/complete_case.py
impyute/imputation/__init__.py
impyute/imputation/cs/__init__.py
impyute/imputation/cs/central_tendency.py
impyute/imputation/cs/em.py
impyute/imputation/cs/fast_knn.py
impyute/imputation/cs/mice.py
impyute/imputation/cs/random.py
impyute/imputation/ts/__init__.py
impyute/imputation/ts/locf.py
impyute/imputation/ts/moving_window.py
impyute/util/__init__.py
impyute/util/checks.py
impyute/util/compare.py
impyute/util/count_missing.py
impyute/util/describe.py
impyute/util/errors.py
impyute/util/find_null.py
impyute/util/mcar_test.py
impyute/util/preprocess.py
test/__init__.py
test/dataset/__init__.py
test/dataset/test_mnist.py
test/deletion/__init__.py
test/deletion/test_complete_case.py
test/imputation/__init__.py
test/imputation/cs/__init__.py
test/imputation/cs/test_central_tendency.py
test/imputation/cs/test_em.py
test/imputation/cs/test_fast_knn.py
test/imputation/cs/test_mice.py
test/imputation/cs/test_random.py
test/imputation/ts/__init__.py
test/imputation/ts/test_arima.py
test/imputation/ts/test_locf.py
test/imputation/ts/test_moving_window.py
test/util/__init__.py
test/util/test_checks.py
test/util/test_compare.py
test/util/test_preprocess.py
impyute-0.0.8.dist-info/AUTHORS.rst
impyute-0.0.8.dist-info/LICENSE
impyute-0.0.8.dist-info/METADATA
impyute-0.0.8.dist-info/WHEEL
impyute-0.0.8.dist-info/top_level.txt
impyute-0.0.8.dist-info/RECORD
