Metadata-Version: 2.1
Name: impyute
Version: 0.0.8
Summary: Cross-sectional and time-series data imputation algorithms
Home-page: http://impyute.readthedocs.io/en/latest/
Author: Elton Law
Author-email: eltonlaw296@gmail.com
License: GPL-3.0
Download-URL: https://github.com/eltonlaw/impyute
Keywords: imputation
Platform: UNKNOWN
Classifier: Development Status :: 3 - Alpha
Classifier: Intended Audience :: Science/Research
Classifier: Intended Audience :: Developers
Classifier: Programming Language :: Python
Classifier: Topic :: Software Development
Classifier: Topic :: Scientific/Engineering
Provides-Extra: test
Provides-Extra: dev
